{
	"name": "greenpeace/planet4-test-sinope",
	"description": "Greenpeace P4 test-sinope",
	"license": "MIT",
	"require": {
		"greenpeace/planet4-master-theme": "dev-master",
		"greenpeace/planet4-plugin-gutenberg-blocks": "7"
	},
	"scripts": {
		"site:custom": []
	},
	"repositories": [
		{
			"type": "package",
			"package": {
				"name": "greenpeace/planet4-plugin-gutenberg-blocks",
				"type": "wordpress-plugin",
				"autoload": null,
				"extra": null,
				"version": 7,
				"dist": {
					"type": "zip",
					"url": "https://storage.googleapis.com/planet4-packages/planet4-plugin-gutenberg-blocks/f88ad93b8b86447c57048f973fd5cc1c3dc7dd31.zip"
				}
			}
		}
	]
}
